oplab/__init__.py
oplab/errors.py
oplab/v3/__init__.py
oplab/v3/domain.py
oplab/v3/market.py
oplab/v3/quant.py
oplab_client_python-0.2.7.dist-info/LICENSE
oplab_client_python-0.2.7.dist-info/METADATA
oplab_client_python-0.2.7.dist-info/WHEEL
oplab_client_python-0.2.7.dist-info/top_level.txt
oplab_client_python-0.2.7.dist-info/RECORD
