Metadata-Version: 2.1
Name: oplab-client-python
Version: 0.2.7
Summary: Oplab's API Client Package
Home-page: https://github.com/oplab-team/oplab-client-python
Author: César Vargas
Author-email: cesar@oplab.com.br
License: UNKNOWN
Platform: UNKNOWN
Classifier: Programming Language :: Python :: 3
Classifier: License :: OSI Approved :: MIT License
Classifier: Operating System :: OS Independent
Requires-Python: >=3.7.5
Requires-Dist: requests
